ckan_client_tacc/__init__.py
ckan_client_tacc/__main__.py
ckan_client_tacc/client/datasets/create.py
ckan_client_tacc/client/datasets/get.py
ckan_client_tacc/client/datasets/list.py
ckan_client_tacc/client/organizations/create.py
ckan_client_tacc/client/organizations/members/add.py
ckan_client_tacc/client/resources/create.py
ckan_client_tacc/client/users/create.py
ckan_client_tacc/client/users/get.py
ckan_client_tacc/client/users/list.py
ckan_client_tacc/dataset_subcommand.py
ckan_client_tacc/example.py
ckan_client_tacc/models/UserMapper.py
ckan_client_tacc/models/ckan/responses/member_response.py
ckan_client_tacc/models/ckan/user.py
ckan_client_tacc/models/portalx/user.py
ckan_client_tacc/organization_subcommand.py
ckan_client_tacc/user_subcommand.py
ckan_client_tacc-0.1.0.dist-info/LICENSE
ckan_client_tacc-0.1.0.dist-info/METADATA
ckan_client_tacc-0.1.0.dist-info/WHEEL
ckan_client_tacc-0.1.0.dist-info/entry_points.txt
ckan_client_tacc-0.1.0.dist-info/RECORD
