Metadata-Version: 2.1
Name: ckan-client-tacc
Version: 0.1.0
Summary: Awesome `ckan-client-tacc` is a Python cli/package created with https://github.com/Undertone0809/python-package-template
Home-page: https://github.com/in_for_disaster_analytics/ckan-client-tacc
License: MIT
Author: In-For-Disaster-Analytics
Author-email: maxiosorio@gmail.com
Requires-Python: >=3.9,<4.0
Classifier: Development Status :: 3 - Alpha
Classifier: Intended Audience :: Developers
Classifier: License :: OSI Approved :: MIT License
Classifier: Operating System :: OS Independent
Classifier: Programming Language :: Python :: 3
Classifier: Programming Language :: Python :: 3.9
Classifier: Programming Language :: Python :: 3.10
Classifier: Programming Language :: Python :: 3.11
Classifier: Programming Language :: Python :: 3.12
Classifier: Programming Language :: Python :: 3.13
Classifier: Topic :: Software Development :: Libraries :: Python Modules
Requires-Dist: requests (>=2.32.3,<3.0.0)
Requires-Dist: rich (>=10.14.0,<11.0.0)
Requires-Dist: typer[all] (>=0.4.0,<0.5.0)
Project-URL: Repository, https://github.com/in_for_disaster_analytics/ckan-client-tacc
